{
  "spelers": [
    {
      "naam": "Lars Linksback",
      "email": "lars.linksback@example.com",
      "land": [
        "BE",
        "NL"
      ],
      "regio": "Limburg (BE)",
      "geboortejaar": 2008,
      "geslacht": "Heren",
      "leeftijdscategorie": "U17",
      "niveau": "Jeugd – provinciaal (BE)",
      "positie": "Linksback / linker wingback",
      "beschikbaarheid": "Vanaf volgend seizoen",
      "minderjarig_ouder": true,
      "cv": "",
      "foto": "assets/img/spelers/lars-linksback.jpg",
      "video": "https://www.youtube.com/watch?v=dQw4w9WgXcQ",
      "profieltekst": "Snel, duelkrachtig en conditioneel sterk. Speelt graag aanvallend mee.",
      "tags": [
        "U17",
        "Limburg",
        "Linksback"
      ],
      "status": "approved"
    },
    {
      "naam": "Mila Midfielder",
      "email": "mila.midfielder@example.com",
      "land": [
        "NL"
      ],
      "regio": "Utrecht",
      "geboortejaar": 2005,
      "geslacht": "Dames",
      "leeftijdscategorie": "Eerste elftal dames",
      "niveau": "Dames – alle niveaus",
      "positie": "Centrale middenvelder",
      "beschikbaarheid": "Direct beschikbaar",
      "minderjarig_ouder": false,
      "cv": "",
      "foto": "assets/img/spelers/mila-midfielder.png",
      "video": "",
      "profieltekst": "Inzichtelijke spelverdeler met goede passing en loopvermogen.",
      "tags": [
        "Dames",
        "Middenveld"
      ],
      "status": "approved"
    }
  ]
}